awslabs/__init__.py
awslabs/aws_healthomics_mcp_server/__init__.py
awslabs/aws_healthomics_mcp_server/consts.py
awslabs/aws_healthomics_mcp_server/server.py
awslabs/aws_healthomics_mcp_server/analysis/__init__.py
awslabs/aws_healthomics_mcp_server/analysis/cost_analyzer.py
awslabs/aws_healthomics_mcp_server/analysis/instance_recommender.py
awslabs/aws_healthomics_mcp_server/analysis/pricing_cache.py
awslabs/aws_healthomics_mcp_server/analysis/task_aggregator.py
awslabs/aws_healthomics_mcp_server/models/__init__.py
awslabs/aws_healthomics_mcp_server/models/analysis.py
awslabs/aws_healthomics_mcp_server/models/core.py
awslabs/aws_healthomics_mcp_server/models/s3.py
awslabs/aws_healthomics_mcp_server/models/search.py
awslabs/aws_healthomics_mcp_server/search/__init__.py
awslabs/aws_healthomics_mcp_server/search/file_association_engine.py
awslabs/aws_healthomics_mcp_server/search/file_type_detector.py
awslabs/aws_healthomics_mcp_server/search/genomics_search_orchestrator.py
awslabs/aws_healthomics_mcp_server/search/healthomics_search_engine.py
awslabs/aws_healthomics_mcp_server/search/json_response_builder.py
awslabs/aws_healthomics_mcp_server/search/pattern_matcher.py
awslabs/aws_healthomics_mcp_server/search/result_ranker.py
awslabs/aws_healthomics_mcp_server/search/s3_search_engine.py
awslabs/aws_healthomics_mcp_server/search/scoring_engine.py
awslabs/aws_healthomics_mcp_server/tools/__init__.py
awslabs/aws_healthomics_mcp_server/tools/genomics_file_search.py
awslabs/aws_healthomics_mcp_server/tools/helper_tools.py
awslabs/aws_healthomics_mcp_server/tools/run_analysis.py
awslabs/aws_healthomics_mcp_server/tools/run_timeline.py
awslabs/aws_healthomics_mcp_server/tools/troubleshooting.py
awslabs/aws_healthomics_mcp_server/tools/workflow_analysis.py
awslabs/aws_healthomics_mcp_server/tools/workflow_execution.py
awslabs/aws_healthomics_mcp_server/tools/workflow_linting.py
awslabs/aws_healthomics_mcp_server/tools/workflow_management.py
awslabs_aws_healthomics_mcp_server-0.0.22.dist-info/METADATA
awslabs_aws_healthomics_mcp_server-0.0.22.dist-info/WHEEL
awslabs_aws_healthomics_mcp_server-0.0.22.dist-info/entry_points.txt
awslabs_aws_healthomics_mcp_server-0.0.22.dist-info/licenses/LICENSE
awslabs_aws_healthomics_mcp_server-0.0.22.dist-info/licenses/NOTICE
awslabs_aws_healthomics_mcp_server-0.0.22.dist-info/RECORD
