Metadata-Version: 2.4
Name: awslabs.aws-healthomics-mcp-server
Version: 0.0.22
Summary: An AWS Labs Model Context Protocol (MCP) server for AWS HealthOmics
Project-URL: homepage, https://awslabs.github.io/mcp/
Project-URL: docs, https://awslabs.github.io/mcp/servers/aws-healthomics-mcp-server/
Project-URL: documentation, https://awslabs.github.io/mcp/servers/aws-healthomics-mcp-server/
Project-URL: repository, https://github.com/awslabs/mcp.git
Project-URL: changelog, https://github.com/awslabs/mcp/blob/main/src/aws-healthomics-mcp-server/CHANGELOG.md
Author: Amazon Web Services
Author-email: AWSLabs MCP <203918161+awslabs-mcp@users.noreply.github.com>, Your Name <githubusername@users.noreply.github.com>
License: Apache-2.0
License-File: LICENSE
License-File: NOTICE
Classifier: License :: OSI Approved :: Apache Software License
Classifier: Operating System :: OS Independent
Classifier: Programming Language :: Python
Classifier: Programming Language :: Python :: 3
Classifier: Programming Language :: Python :: 3.10
Classifier: Programming Language :: Python :: 3.11
Classifier: Programming Language :: Python :: 3.12
Classifier: Programming Language :: Python :: 3.13
Requires-Python: >=3.10
Requires-Dist: boto3>=1.40.23
Requires-Dist: coloredlogs>=15.0
Requires-Dist: cwltool[deps]>=3.1.0
Requires-Dist: isodate>=0.6.0
Requires-Dist: loguru>=0.7.0
Requires-Dist: mcp[cli]>=1.23.0
Requires-Dist: miniwdl>=1.12.0
Requires-Dist: nest-asyncio>=1.5.0
Requires-Dist: polars>=1.0.0
Requires-Dist: pydantic>=2.10.6
Requires-Dist: ruamel-yaml>=0.18.0
